basicParallelize/__init__.py
basicParallelize/_helpers.py
basicParallelize/_parallelize.py
basicParallelize/_parallelizeTQDM.py
basicparallelize-1.1.3.dist-info/licenses/LICENSE
basicparallelize-1.1.3.dist-info/METADATA
basicparallelize-1.1.3.dist-info/WHEEL
basicparallelize-1.1.3.dist-info/top_level.txt
basicparallelize-1.1.3.dist-info/RECORD
