Metadata-Version: 2.4
Name: basicParallelize
Version: 1.1.3
Summary: Wrappers for multiprocessing's Pool and ThreadPool classes.
Author-email: Joshua Beale <jbeale2023@gmail.com>
License: MIT
Project-URL: Homepage, https://github.com/jBeale23/parallelize
Keywords: parallel
Classifier: Intended Audience :: Developers
Classifier: Programming Language :: Python
Classifier: Programming Language :: Python :: 3
Classifier: Programming Language :: Python :: 3.8
Classifier: Programming Language :: Python :: 3.9
Classifier: Programming Language :: Python :: 3.10
Classifier: Programming Language :: Python :: 3.11
Classifier: Programming Language :: Python :: 3.12
Classifier: Programming Language :: Python :: 3.13
Classifier: Operating System :: OS Independent
Classifier: Topic :: Utilities
Requires-Python: >=3.8
License-File: LICENSE
Requires-Dist: tqdm>=2.0.0
Dynamic: license-file
